alibabacloud_agency20221216/__init__.py
alibabacloud_agency20221216/client.py
alibabacloud_agency20221216/models/__init__.py
alibabacloud_agency20221216/models/_cancel_coupon_request.py
alibabacloud_agency20221216/models/_cancel_coupon_response.py
alibabacloud_agency20221216/models/_cancel_coupon_response_body.py
alibabacloud_agency20221216/models/_cancel_subscription_bill_request.py
alibabacloud_agency20221216/models/_cancel_subscription_bill_response.py
alibabacloud_agency20221216/models/_cancel_subscription_bill_response_body.py
alibabacloud_agency20221216/models/_coupon_approval_status_list_request.py
alibabacloud_agency20221216/models/_coupon_approval_status_list_response.py
alibabacloud_agency20221216/models/_coupon_approval_status_list_response_body.py
alibabacloud_agency20221216/models/_create_coupon_template_request.py
alibabacloud_agency20221216/models/_create_coupon_template_response.py
alibabacloud_agency20221216/models/_create_coupon_template_response_body.py
alibabacloud_agency20221216/models/_create_coupon_template_shrink_request.py
alibabacloud_agency20221216/models/_create_customer_request.py
alibabacloud_agency20221216/models/_create_customer_response.py
alibabacloud_agency20221216/models/_create_customer_response_body.py
alibabacloud_agency20221216/models/_customer_quota_record_list_request.py
alibabacloud_agency20221216/models/_customer_quota_record_list_response.py
alibabacloud_agency20221216/models/_customer_quota_record_list_response_body.py
alibabacloud_agency20221216/models/_deduct_outstanding_balance_request.py
alibabacloud_agency20221216/models/_deduct_outstanding_balance_response.py
alibabacloud_agency20221216/models/_deduct_outstanding_balance_response_body.py
alibabacloud_agency20221216/models/_delete_coupon_template_request.py
alibabacloud_agency20221216/models/_delete_coupon_template_response.py
alibabacloud_agency20221216/models/_delete_coupon_template_response_body.py
alibabacloud_agency20221216-1.9.0.dist-info/LICENSE
alibabacloud_agency20221216-1.9.0.dist-info/METADATA
alibabacloud_agency20221216-1.9.0.dist-info/WHEEL
alibabacloud_agency20221216-1.9.0.dist-info/top_level.txt
alibabacloud_agency20221216-1.9.0.dist-info/RECORD
